fastairport/__init__.py
fastairport/client.py
fastairport/context.py
fastairport/errors.py
fastairport/py.typed
fastairport/server.py
fastairport/cli/__init__.py
fastairport/cli/main.py
fastairport-0.2.0.dist-info/METADATA
fastairport-0.2.0.dist-info/WHEEL
fastairport-0.2.0.dist-info/entry_points.txt
fastairport-0.2.0.dist-info/licenses/LICENSE
fastairport-0.2.0.dist-info/RECORD
